image2patch/__init__.py
image2patch/patchutils.py
image2patch-0.1.0.dist-info/LICENSE
image2patch-0.1.0.dist-info/WHEEL
image2patch-0.1.0.dist-info/METADATA
image2patch-0.1.0.dist-info/RECORD
