Metadata-Version: 2.1
Name: image2patch
Version: 0.1.0
Summary: A library that splits the image into overlapping or non-overlapping patches with the optimal step in order to minimize pixels loss. It can then merge them back together.
Home-page: https://github.com/LucaPavirani/image2patch.py
License: MIT
Keywords: patch,split,augmentation,image,overlap
Author: Luca Pavirani
Author-email: luca481998@gmail.com
Requires-Python: >=3.7,<4.0
Classifier: Intended Audience :: Developers
Classifier: License :: OSI Approved :: MIT License
Classifier: Programming Language :: Python :: 3
Classifier: Programming Language :: Python :: 3.7
Classifier: Programming Language :: Python :: 3.8
Classifier: Programming Language :: Python :: 3.9
Classifier: Programming Language :: Python :: 3.10
Classifier: Programming Language :: Python :: 3.11
Classifier: Topic :: Multimedia :: Graphics :: Editors
Requires-Dist: numpy (>=1,<2)
Project-URL: Repository, https://github.com/LucaPavirani/image2patch.py
